css_colors_stats/__init__.py
css_colors_stats/core.py
css_colors_stats/html.py
css_colors_stats/parser.py
css_colors_stats-0.0.3.dist-info/METADATA
css_colors_stats-0.0.3.dist-info/WHEEL
css_colors_stats-0.0.3.dist-info/entry_points.txt
css_colors_stats-0.0.3.dist-info/RECORD
