Metadata-Version: 2.1
Name: css-colors-stats
Version: 0.0.3
Summary: Quickly extract and count colors from CSS files.
Author: Giorgio Caizzi
Author-email: giorgio.caizzi@jakala.com
Requires-Python: >=3.9,<4.0
Classifier: Programming Language :: Python :: 3
Classifier: Programming Language :: Python :: 3.9
Classifier: Programming Language :: Python :: 3.10
Classifier: Programming Language :: Python :: 3.11
Classifier: Programming Language :: Python :: 3.12
